LICENSE
MANIFEST.in
README.rst
setup.py
version.txt
aiopubsub/__init__.py
aiopubsub/logging_compat.py
aiopubsub/loop.py
aiopubsub.egg-info/PKG-INFO
aiopubsub.egg-info/SOURCES.txt
aiopubsub.egg-info/dependency_links.txt
aiopubsub.egg-info/requires.txt
aiopubsub.egg-info/top_level.txt
aiopubsub/testing/__init__.py
aiopubsub/testing/mocks.py