Metadata-Version: 1.1
Name: aiopubsub
Version: 1.0.0
Summary: Simple pubsub pattern for asyncio applications
Home-page: https://github.com/qntln/aiopubsub
Author: Quantlane
Author-email: code@quantlane.com
License: Apache 2.0
Platform: UNKNOWN
Classifier: Development Status :: 4 - Beta
Classifier: License :: OSI Approved :: Apache Software License
Classifier: Natural Language :: English
Classifier: Programming Language :: Python :: 3 :: Only
Classifier: Programming Language :: Python :: 3.5
